vsipc_tools/__init__.py
vsipc_tools/base_rest_client.py
vsipc_tools/utils.py
vsipc_tools-1.3.dist-info/LICENSE.txt
vsipc_tools-1.3.dist-info/METADATA
vsipc_tools-1.3.dist-info/WHEEL
vsipc_tools-1.3.dist-info/top_level.txt
vsipc_tools-1.3.dist-info/RECORD
