Metadata-Version: 2.1
Name: vsipc-tools
Version: 1.3
Summary: Useful tools implemented by Vitalii Sipchenko
Home-page: https://bitbucket.org/vsipchenko/vsipc_tools/
Author: Vitalii Sipchenko
Author-email: vitaliisipchenko@gmail.com
License: MIT
Download-URL: https://bitbucket.org/vsipchenko/vsipc_tools/
Keywords: VsipcTools,vsipctools
Platform: UNKNOWN
Requires-Dist: pytest (==5.4.1)
Requires-Dist: aiohttp (==3.6.2)
